LICENSE
MANIFEST.in
README
convert.py
setup.py
track.py
Git_Track.egg-info/PKG-INFO
Git_Track.egg-info/SOURCES.txt
Git_Track.egg-info/dependency_links.txt
Git_Track.egg-info/requires.txt
Git_Track.egg-info/top_level.txt
issue_db/__init__.py
issue_db/issue_db.py