Metadata-Version: 1.0
Name: Git-Track
Version: 0.1
Summary: Minimal Bug Tracking For Git.
Home-page: http://github.com/dhesse/Git-Track
Author: Dirk Hesse
Author-email: herr.dirk.hesse@gmail.com
License: MIT
Platform: UNKNOWN
Classifier: Development Status :: 4 - Beta
Classifier: Environment :: Console
Classifier: Intended Audience :: Developers
Classifier: Intended Audience :: Science/Research
Classifier: License :: OSI Approved :: MIT License
Classifier: Natural Language :: English
Classifier: Topic :: Software Development :: Bug Tracking
Classifier: Topic :: Software Development :: Version Control
Classifier: Operating System :: OS Independent
Classifier: Programming Language :: Python :: 2.6
Classifier: Programming Language :: Python :: 2.7
